villaProductDatabase/None.py
villaProductDatabase/__init__.py
villaProductDatabase/_nbdev.py
villaProductDatabase/database.py
villaProductDatabase/helper.py
villaProductDatabase/helpers.py
villaProductDatabase/query.py
villaProductDatabase/s3.py
villaProductDatabase/schema.py
villaProductDatabase/update.py
villaProductDatabase-0.0.50.dist-info/LICENSE
villaProductDatabase-0.0.50.dist-info/METADATA
villaProductDatabase-0.0.50.dist-info/WHEEL
villaProductDatabase-0.0.50.dist-info/entry_points.txt
villaProductDatabase-0.0.50.dist-info/top_level.txt
villaProductDatabase-0.0.50.dist-info/RECORD
