Metadata-Version: 2.1
Name: villaProductDatabase
Version: 0.0.50
Summary: product database management functions
Home-page: https://github.com/thanakijwanavit/villaProductDatabase/tree/master/
Author: Nic Wanavit
Author-email: nwanavit@hatari.cc
License: Apache Software License 2.0
Keywords: product database
Platform: UNKNOWN
Classifier: Development Status :: 3 - Alpha
Classifier: Intended Audience :: Developers
Classifier: License :: OSI Approved :: Apache Software License
Classifier: Natural Language :: English
Classifier: Programming Language :: Python :: 3.6
Classifier: Programming Language :: Python :: 3.7
Classifier: Programming Language :: Python :: 3.8
Requires-Python: >=3.6
Requires-Dist: linesdk
Requires-Dist: dict-hash
Requires-Dist: s3bz
Requires-Dist: boto3
Requires-Dist: awsSchema
Requires-Dist: dataclasses-json
Requires-Dist: requests
